yeedu/__init__.py
yeedu/hooks/__init__.py
yeedu/hooks/yeedu.py
yeedu/operators/__init__.py
yeedu/operators/yeedu.py
yeedu_operator_test-0.0.5.dist-info/LICENSE
yeedu_operator_test-0.0.5.dist-info/METADATA
yeedu_operator_test-0.0.5.dist-info/WHEEL
yeedu_operator_test-0.0.5.dist-info/top_level.txt
yeedu_operator_test-0.0.5.dist-info/RECORD
